ebcdic_parser/__init__.py
ebcdic_parser/__main__.py
ebcdic_parser/convert.py
ebcdic_parser-3.4.0.dist-info/AUTHORS
ebcdic_parser-3.4.0.dist-info/LICENSE
ebcdic_parser-3.4.0.dist-info/METADATA
ebcdic_parser-3.4.0.dist-info/WHEEL
ebcdic_parser-3.4.0.dist-info/top_level.txt
ebcdic_parser-3.4.0.dist-info/RECORD
