Metadata-Version: 2.1
Name: ebcdic-parser
Version: 3.4.0
Summary: Convert mainframe EBCDIC data into Unicode ASCII delimited text files
Home-page: https://github.com/larandvit/ebcdic-parser
Author: Vitaly Saversky
Author-email: larandvit@hotmail.com
Project-URL: Bug Tracker, https://github.com/larandvit/ebcdic-parser/issues
Project-URL: repository, https://github.com/larandvit/ebcdic-parser
Classifier: Programming Language :: Python :: 3
Classifier: License :: OSI Approved :: MIT License
Classifier: Operating System :: OS Independent
Requires-Python: >=3.7
License-File: LICENSE
License-File: AUTHORS
